csv_linter/__init__.py
csv_linter/main.py
jae_csv_linter-0.0.4.dist-info/METADATA
jae_csv_linter-0.0.4.dist-info/WHEEL
jae_csv_linter-0.0.4.dist-info/entry_points.txt
jae_csv_linter-0.0.4.dist-info/top_level.txt
jae_csv_linter-0.0.4.dist-info/RECORD
