Metadata-Version: 2.4
Name: jae-csv-linter
Version: 0.0.4
Summary: demo python CLI tool to lint csv files
Requires-Python: >=3.8
Requires-Dist: click>=8.1.3
Requires-Dist: flake8==3.8.4
Requires-Dist: mccabe==0.6.1
Requires-Dist: pandas>=1.5.3
Requires-Dist: pycodestyle==2.6.0
Requires-Dist: pyflakes==2.2.0
Requires-Dist: python-dateutil>=2.8.2
Requires-Dist: pytz>=2020.5
Requires-Dist: six>=1.15.0
Requires-Dist: numpy>=1.22.4
Dynamic: requires-dist
Dynamic: requires-python
Dynamic: summary
